README.rst
setup.py
djcities/__init__.py
djcities/admin.py
djcities/models.py
djcities/settings.py
djcities/tests.py
djcities/urls.py
djcities/views.py
djcities.egg-info/PKG-INFO
djcities.egg-info/SOURCES.txt
djcities.egg-info/dependency_links.txt
djcities.egg-info/not-zip-safe
djcities.egg-info/top_level.txt
djcities/management/__init__.py
djcities/management/commands/__init__.py
djcities/management/commands/generate_translations.py
djcities/management/commands/make_cities_messages.py
djcities/management/commands/populate_cities.py