Metadata-Version: 1.1
Name: djcities
Version: 0.1
Summary: A full database of contry/state/city/timezone for django. Based on django-cities but
Home-page: https://github.com/niwibe/djcities
Author: Andrey Antukh
Author-email: niwi@niwi.be
License: UNKNOWN
Platform: UNKNOWN
Classifier: Development Status :: 4 - Beta
Classifier: Operating System :: OS Independent
Classifier: Environment :: Web Environment
Classifier: Framework :: Django
Classifier: License :: OSI Approved :: BSD License
Classifier: Intended Audience :: Developers
Classifier: Programming Language :: Python
Classifier: Programming Language :: Python :: 2
Classifier: Programming Language :: Python :: 2.7
Classifier: Topic :: Software Development :: Libraries
Classifier: Topic :: Utilities
